{
	"credit": "Made with Blockbench",
	"parent": "minecraft:block/door_top",
	"textures": {
		"top": "block/spruce_door_top"
	},
	"elements": [
		{
			"from": [0, 0, 13],
			"to": [3, 16, 15],
			"rotation": {"angle": 0, "axis": "y", "origin": [1.5, 8, 8]},
			"faces": {
				"north": {"uv": [13, 0, 15, 16], "texture": "#top"},
				"east": {"uv": [13, 0, 15, 16], "texture": "#top"},
				"south": {"uv": [13, 0, 15, 16], "texture": "#top"},
				"west": {"uv": [13, 0, 15, 16], "texture": "#top"},
				"up": {"uv": [13, 0, 15, 3], "rotation": 270, "texture": "#top"},
				"down": {"uv": [13, 12, 15, 15], "rotation": 270, "texture": "#top"}
			}
		},
		{
			"from": [0.5, 0, 15],
			"to": [2.5, 16, 16],
			"rotation": {"angle": 0, "axis": "y", "origin": [1.5, 8, 8]},
			"faces": {
				"north": {"uv": [0, 0, 2, 16], "texture": "#missing"},
				"east": {"uv": [15, 0, 16, 16], "texture": "#top"},
				"south": {"uv": [13, 0, 15, 16], "texture": "#top"},
				"west": {"uv": [15, 0, 16, 16], "texture": "#top"},
				"up": {"uv": [15, 0, 16, 2], "rotation": 270, "texture": "#top"},
				"down": {"uv": [15, 14, 16, 16], "rotation": 270, "texture": "#top"}
			}
		},
		{
			"from": [0, 0, 10],
			"to": [3, 16, 12],
			"rotation": {"angle": 0, "axis": "y", "origin": [1.5, 8, 8]},
			"faces": {
				"north": {"uv": [4, 0, 6, 16], "texture": "#top"},
				"east": {"uv": [4, 0, 6, 16], "texture": "#top"},
				"south": {"uv": [4, 0, 6, 16], "texture": "#top"},
				"west": {"uv": [4, 0, 6, 16], "texture": "#top"},
				"up": {"uv": [10, 0, 12, 3], "rotation": 270, "texture": "#top"},
				"down": {"uv": [10, 12, 12, 15], "rotation": 270, "texture": "#top"}
			}
		},
		{
			"from": [0.5, 0, 12],
			"to": [2.5, 16, 13],
			"rotation": {"angle": 0, "axis": "y", "origin": [1.5, 8, 8]},
			"faces": {
				"north": {"uv": [0, 0, 2, 16], "texture": "#missing"},
				"east": {"uv": [12, 0, 13, 16], "texture": "#top"},
				"south": {"uv": [0, 0, 2, 16], "texture": "#missing"},
				"west": {"uv": [12, 0, 13, 16], "texture": "#top"},
				"up": {"uv": [12, 0, 13, 2], "rotation": 270, "texture": "#top"},
				"down": {"uv": [12, 14, 13, 16], "rotation": 270, "texture": "#top"}
			}
		},
		{
			"from": [0, 0, 7],
			"to": [3, 16, 9],
			"rotation": {"angle": 0, "axis": "y", "origin": [1.5, 8, 8]},
			"faces": {
				"north": {"uv": [4, 0, 6, 16], "texture": "#top"},
				"east": {"uv": [4, 0, 6, 16], "texture": "#top"},
				"south": {"uv": [4, 0, 6, 16], "texture": "#top"},
				"west": {"uv": [4, 0, 6, 16], "texture": "#top"},
				"up": {"uv": [7, 0, 9, 3], "rotation": 270, "texture": "#top"},
				"down": {"uv": [4, 12, 6, 15], "rotation": 270, "texture": "#top"}
			}
		},
		{
			"from": [0.5, 0, 9],
			"to": [2.5, 16, 10],
			"rotation": {"angle": 0, "axis": "y", "origin": [1.5, 8, 8]},
			"faces": {
				"north": {"uv": [0, 0, 2, 16], "texture": "#missing"},
				"east": {"uv": [9, 0, 10, 16], "texture": "#top"},
				"south": {"uv": [0, 0, 2, 16], "texture": "#missing"},
				"west": {"uv": [9, 0, 10, 16], "texture": "#top"},
				"up": {"uv": [9, 0, 10, 2], "rotation": 270, "texture": "#top"},
				"down": {"uv": [9, 14, 10, 16], "rotation": 270, "texture": "#top"}
			}
		},
		{
			"from": [0, 0, 4],
			"to": [3, 16, 6],
			"rotation": {"angle": 0, "axis": "y", "origin": [1.5, 8, 8]},
			"faces": {
				"north": {"uv": [4, 0, 6, 16], "texture": "#top"},
				"east": {"uv": [4, 0, 6, 16], "texture": "#top"},
				"south": {"uv": [4, 0, 6, 16], "texture": "#top"},
				"west": {"uv": [4, 0, 6, 16], "texture": "#top"},
				"up": {"uv": [4, 0, 6, 3], "rotation": 270, "texture": "#top"},
				"down": {"uv": [4, 12, 6, 15], "rotation": 270, "texture": "#top"}
			}
		},
		{
			"from": [0.5, 0, 6],
			"to": [2.5, 16, 7],
			"rotation": {"angle": 0, "axis": "y", "origin": [1.5, 8, 8]},
			"faces": {
				"north": {"uv": [0, 0, 2, 16], "texture": "#missing"},
				"east": {"uv": [9, 0, 10, 16], "texture": "#top"},
				"south": {"uv": [0, 0, 2, 16], "texture": "#missing"},
				"west": {"uv": [6, 0, 7, 16], "texture": "#top"},
				"up": {"uv": [6, 0, 7, 2], "rotation": 270, "texture": "#top"},
				"down": {"uv": [6, 14, 7, 16], "rotation": 270, "texture": "#top"}
			}
		},
		{
			"from": [0.5, 0, 3],
			"to": [2.5, 16, 4],
			"rotation": {"angle": 0, "axis": "y", "origin": [1.5, 8, 8]},
			"faces": {
				"north": {"uv": [0, 0, 2, 16], "texture": "#missing"},
				"east": {"uv": [9, 0, 10, 16], "texture": "#top"},
				"south": {"uv": [0, 0, 2, 16], "texture": "#missing"},
				"west": {"uv": [3, 0, 4, 16], "texture": "#top"},
				"up": {"uv": [3, 0, 4, 2], "rotation": 270, "texture": "#top"},
				"down": {"uv": [3, 14, 4, 16], "rotation": 270, "texture": "#top"}
			}
		},
		{
			"from": [0, 0, 1],
			"to": [3, 16, 3],
			"rotation": {"angle": 0, "axis": "y", "origin": [1.5, 8, 8]},
			"faces": {
				"north": {"uv": [1, 0, 3, 16], "texture": "#top"},
				"east": {"uv": [1, 0, 3, 16], "texture": "#top"},
				"south": {"uv": [1, 0, 3, 16], "texture": "#top"},
				"west": {"uv": [1, 0, 3, 16], "texture": "#top"},
				"up": {"uv": [1, 0, 3, 3], "rotation": 270, "texture": "#top"},
				"down": {"uv": [1, 12, 3, 15], "rotation": 270, "texture": "#top"}
			}
		},
		{
			"from": [0.5, 0, 0],
			"to": [2.5, 16, 1],
			"rotation": {"angle": 0, "axis": "y", "origin": [1.5, 8, 8]},
			"faces": {
				"north": {"uv": [13, 0, 15, 16], "texture": "#top"},
				"east": {"uv": [0, 0, 1, 16], "texture": "#top"},
				"south": {"uv": [0, 0, 2, 16], "texture": "#missing"},
				"west": {"uv": [0, 0, 1, 16], "texture": "#top"},
				"up": {"uv": [0, 0, 1, 2], "rotation": 270, "texture": "#top"},
				"down": {"uv": [0, 14, 1, 16], "rotation": 270, "texture": "#top"}
			}
		}
	]
}